AUTHORS
LICENSE
MANIFEST.in
README.rst
TODO.rst
setup.py
djaboto/__init__.py
djaboto/__init__.pyc
djaboto/debian.py
djaboto/debian.pyc
djaboto/pve.py
djaboto/pve.pyc
djaboto/management/__init__.py
djaboto/management/__init__.pyc
djaboto/management/base.pyc
djaboto/management/commands/__init__.py
djaboto/management/commands/__init__.pyc
djaboto/management/commands/aws.py
djaboto/management/commands/aws.pyc
djaboto/management/commands/checkmix.py
djaboto/management/commands/checkmix.pyc
djaboto/management/commands/cmsplugins.py
djaboto/management/commands/cmsplugins.pyc
djaboto/management/commands/mix.pyc
django_djaboto.egg-info/PKG-INFO
django_djaboto.egg-info/SOURCES.txt
django_djaboto.egg-info/dependency_links.txt
django_djaboto.egg-info/entry_points.txt
django_djaboto.egg-info/not-zip-safe
django_djaboto.egg-info/requires.txt
django_djaboto.egg-info/top_level.txt