Metadata-Version: 1.1
Name: django-djaboto
Version: 0.0.6a3
Summary: A Django app and assorted tools to help create, deploy and manage Django projects on AWS servers
Home-page: https://bitbucket.org/oddotterco/django-djaboto
Author: Odd Otter Co
Author-email: djaboto@oddotter.com
License: BSD
Keywords: django,cms,amazon
Platform: Linux
Classifier: Development Status :: 2 - Pre-Alpha
Classifier: Framework :: Django
Classifier: Intended Audience :: Developers
Classifier: License :: OSI Approved :: BSD License
Classifier: Operating System :: OS Independent
Classifier: Programming Language :: Python
Classifier: Topic :: Internet :: WWW/HTTP
Classifier: Topic :: Internet :: WWW/HTTP :: Dynamic Content
